MANIFEST.in
README.md
setup.py
myname01/__init__.py
myname01/main.py
myname01.egg-info/PKG-INFO
myname01.egg-info/SOURCES.txt
myname01.egg-info/dependency_links.txt
myname01.egg-info/top_level.txt